marketflow/__db_manager__.py
marketflow/__init__.py
marketflow/market_data.py
marketflow/market_information.py
marketflow/market_registry.py
marketflow/market_ticker.py
marketflow/__data__/database.db
marketflow/__marketconfig__/dataextraction/brvm_data.py
marketflow/__marketconfig__/tickerextraction/brvm_ticker.py
marketflow/__marketconfig__/tickerextraction/bvc_ticker.py
marketflow-1.2.4.dist-info/licenses/LICENSE
marketflow-1.2.4.dist-info/METADATA
marketflow-1.2.4.dist-info/WHEEL
marketflow-1.2.4.dist-info/top_level.txt
marketflow-1.2.4.dist-info/RECORD
