Metadata-Version: 2.4
Name: marketflow
Version: 1.2.4
Summary: Access to African, American, European and Asian market data for financial analysis.
Author-email: ODJO OLABIYI AUREL GEOFFROY <xgeosoft@gmail.com>
Project-URL: Homepage, https://github.com/xgeosoft/marketflow
Keywords: finance,analysis,analytics,statistics,raw data,market,evaluation
Classifier: Programming Language :: Python :: 3
Classifier: License :: OSI Approved :: MIT License
Classifier: Operating System :: OS Independent
Requires-Python: >=3.12
License-File: LICENSE
Requires-Dist: bs4>=0.0.2
Requires-Dist: requests>=2.31.0
Requires-Dist: numpy>=1.9.0
Requires-Dist: pandas>=2.3.0
Requires-Dist: tabulate>=0.9.0
Requires-Dist: certifi>=2025.1.1
Dynamic: license-file
